ndx_survey_data/__init__.py
ndx_survey_data/survey_data.py
ndx_survey_data/survey_definitions.py
ndx_survey_data/spec/ndx-survey-data.extensions.yaml
ndx_survey_data/spec/ndx-survey-data.namespace.yaml
tests/__init__.py
tests/test_ext.py
ndx_survey_data-0.2.0.dist-info/LICENSE.txt
ndx_survey_data-0.2.0.dist-info/METADATA
ndx_survey_data-0.2.0.dist-info/WHEEL
ndx_survey_data-0.2.0.dist-info/top_level.txt
ndx_survey_data-0.2.0.dist-info/RECORD
