Metadata-Version: 2.1
Name: ndx-survey-data
Version: 0.2.0
Summary: NWB extension for survey/ behavioral data
Home-page: https://github.com/catalystneuro/ndx-survey-data
Author: Ben Dichter, Armin Najarpour Foroushani
Author-email: ben.dichter@catalystneuro.com
License: BSD 3-Clause
Platform: UNKNOWN
Classifier: Intended Audience :: Developers
Classifier: Intended Audience :: Science/Research
Requires-Dist: pynwb (>=1.1.2)
